pytorch_es/__init__.py
pytorch_es/strategies/__init__.py
pytorch_es/strategies/evolution.py
pytorch_es/utils/__init__.py
pytorch_es/utils/helpers.py
pytorch_es-0.1.1.dist-info/DESCRIPTION.rst
pytorch_es-0.1.1.dist-info/METADATA
pytorch_es-0.1.1.dist-info/RECORD
pytorch_es-0.1.1.dist-info/WHEEL
pytorch_es-0.1.1.dist-info/metadata.json
pytorch_es-0.1.1.dist-info/top_level.txt
