Metadata-Version: 2.0
Name: pytorch-es
Version: 0.1.1
Summary: Evolutionary Strategies using PyTorch
Home-page: https://github.com/staturecrane/PyTorch-ES
Author: Richard Herbert
Author-email: richard.alan.herbert@gmail.com
License: MIT
Keywords: machine learning,ai,evolutionary strategies,reinforcement learning,pytorch
Platform: UNKNOWN
Classifier: Development Status :: 4 - Beta
Classifier: Intended Audience :: Developers
Classifier: License :: OSI Approved :: Apache Software License
Classifier: Programming Language :: Python
Classifier: Programming Language :: Python :: 3.3
Classifier: Programming Language :: Python :: 3.4
Classifier: Programming Language :: Python :: 3.5
Classifier: Programming Language :: Python :: 3.6
Classifier: Topic :: Internet :: WWW/HTTP
Requires-Dist: evostra (==1.0.1)
Requires-Dist: gym (==0.10.4)
Requires-Dist: gym[box2d] (==0.10.4)
Requires-Dist: gym[atari] (==0.10.4)
Requires-Dist: keras (==2.1.5)
Requires-Dist: numpy (==1.14.2)
Requires-Dist: Pillow (==5.0.0)
Requires-Dist: scikit-image (==0.13.1)
Requires-Dist: tensorflow (==1.6.0)
